{"errors":[],"warnings":["../src/index.ts 1:0-134\n\"export 'IAxes' was not found in './Histogram'","../src/index.ts 2:0-100\n\"export 'IChartPoint' was not found in './LineChart'","../src/index.ts 1:0-134\n\"export 'IHistogramBar' was not found in './Histogram'","../src/index.ts 1:0-134\n\"export 'IHistogramData' was not found in './Histogram'","../src/index.ts 1:0-134\n\"export 'IHistogramDataSet' was not found in './Histogram'","../src/index.ts 1:0-134\n\"export 'IHistogramProps' was not found in './Histogram'","../src/index.ts 2:0-100\n\"export 'ILineChartDataSet' was not found in './LineChart'","../src/index.ts 2:0-100\n\"export 'ILineChartProps' was not found in './LineChart'","../src/index.ts 1:0-134\n\"export 'IStroke' was not found in './Histogram'","./src/pages/map.tsx 36:99-102\n\"export 'Map' was not found in '../../../src'"],"namedChunkGroups":{"app":{"chunks":[13,4],"assets":["webpack-runtime-94647f43a2492d774545.js","webpack-runtime-94647f43a2492d774545.js.map","app-52f7b3a981451ea1c407.js","app-52f7b3a981451ea1c407.js.map"],"children":{},"childAssets":{}},"component---src-pages-404-js":{"chunks":[0,1,5],"assets":["styles.af8dcb6e4833de9aa5ef.css","styles-8c069d83d27a3ec9d5f0.js","styles-8c069d83d27a3ec9d5f0.js.map","1-bf7a1e468358a1ccca34.js","1-bf7a1e468358a1ccca34.js.map","component---src-pages-404-js-74ba5b306cbb7f2c8a66.js","component---src-pages-404-js-74ba5b306cbb7f2c8a66.js.map"],"children":{},"childAssets":{}},"component---src-pages-histogram-tsx":{"chunks":[0,1,2,3,6],"assets":["styles.af8dcb6e4833de9aa5ef.css","styles-8c069d83d27a3ec9d5f0.js","styles-8c069d83d27a3ec9d5f0.js.map","1-bf7a1e468358a1ccca34.js","1-bf7a1e468358a1ccca34.js.map","2-ad6b174e5148675a3605.js","2-ad6b174e5148675a3605.js.map","3-30b331947758fee98f96.js","3-30b331947758fee98f96.js.map","component---src-pages-histogram-tsx-ca130f32a2cc7b9db748.js","component---src-pages-histogram-tsx-ca130f32a2cc7b9db748.js.map"],"children":{},"childAssets":{}},"component---src-pages-index-tsx":{"chunks":[0,1,7],"assets":["styles.af8dcb6e4833de9aa5ef.css","styles-8c069d83d27a3ec9d5f0.js","styles-8c069d83d27a3ec9d5f0.js.map","1-bf7a1e468358a1ccca34.js","1-bf7a1e468358a1ccca34.js.map","component---src-pages-index-tsx-cdd5157118df51d4a4ca.js","component---src-pages-index-tsx-cdd5157118df51d4a4ca.js.map"],"children":{},"childAssets":{}},"component---src-pages-joyplot-tsx":{"chunks":[0,1,2,8],"assets":["styles.af8dcb6e4833de9aa5ef.css","styles-8c069d83d27a3ec9d5f0.js","styles-8c069d83d27a3ec9d5f0.js.map","1-bf7a1e468358a1ccca34.js","1-bf7a1e468358a1ccca34.js.map","2-ad6b174e5148675a3605.js","2-ad6b174e5148675a3605.js.map","component---src-pages-joyplot-tsx-7673184d17e6c4ae4411.js","component---src-pages-joyplot-tsx-7673184d17e6c4ae4411.js.map"],"children":{},"childAssets":{}},"component---src-pages-line-tsx":{"chunks":[0,1,2,3,9],"assets":["styles.af8dcb6e4833de9aa5ef.css","styles-8c069d83d27a3ec9d5f0.js","styles-8c069d83d27a3ec9d5f0.js.map","1-bf7a1e468358a1ccca34.js","1-bf7a1e468358a1ccca34.js.map","2-ad6b174e5148675a3605.js","2-ad6b174e5148675a3605.js.map","3-30b331947758fee98f96.js","3-30b331947758fee98f96.js.map","component---src-pages-line-tsx-f57f7ee6821b57ba78e3.js","component---src-pages-line-tsx-f57f7ee6821b57ba78e3.js.map"],"children":{},"childAssets":{}},"component---src-pages-map-tsx":{"chunks":[0,1,2,3,10],"assets":["styles.af8dcb6e4833de9aa5ef.css","styles-8c069d83d27a3ec9d5f0.js","styles-8c069d83d27a3ec9d5f0.js.map","1-bf7a1e468358a1ccca34.js","1-bf7a1e468358a1ccca34.js.map","2-ad6b174e5148675a3605.js","2-ad6b174e5148675a3605.js.map","3-30b331947758fee98f96.js","3-30b331947758fee98f96.js.map","component---src-pages-map-tsx-214cc2bb04982af33158.js","component---src-pages-map-tsx-214cc2bb04982af33158.js.map"],"children":{},"childAssets":{}},"component---src-pages-pie-tsx":{"chunks":[0,1,2,3,11],"assets":["styles.af8dcb6e4833de9aa5ef.css","styles-8c069d83d27a3ec9d5f0.js","styles-8c069d83d27a3ec9d5f0.js.map","1-bf7a1e468358a1ccca34.js","1-bf7a1e468358a1ccca34.js.map","2-ad6b174e5148675a3605.js","2-ad6b174e5148675a3605.js.map","3-30b331947758fee98f96.js","3-30b331947758fee98f96.js.map","component---src-pages-pie-tsx-64f81f2b2a6e9b78a221.js","component---src-pages-pie-tsx-64f81f2b2a6e9b78a221.js.map"],"children":{},"childAssets":{}},"pages-manifest":{"chunks":[12],"assets":["pages-manifest-7a0fcc4ddfefa33d9874.js","pages-manifest-7a0fcc4ddfefa33d9874.js.map"],"children":{},"childAssets":{}}},"assetsByChunkName":{"app":["webpack-runtime-94647f43a2492d774545.js","app-52f7b3a981451ea1c407.js"],"component---src-pages-404-js":["styles.af8dcb6e4833de9aa5ef.css","styles-8c069d83d27a3ec9d5f0.js","1-bf7a1e468358a1ccca34.js","component---src-pages-404-js-74ba5b306cbb7f2c8a66.js"],"component---src-pages-histogram-tsx":["styles.af8dcb6e4833de9aa5ef.css","styles-8c069d83d27a3ec9d5f0.js","1-bf7a1e468358a1ccca34.js","2-ad6b174e5148675a3605.js","3-30b331947758fee98f96.js","component---src-pages-histogram-tsx-ca130f32a2cc7b9db748.js"],"component---src-pages-index-tsx":["styles.af8dcb6e4833de9aa5ef.css","styles-8c069d83d27a3ec9d5f0.js","1-bf7a1e468358a1ccca34.js","component---src-pages-index-tsx-cdd5157118df51d4a4ca.js"],"component---src-pages-joyplot-tsx":["styles.af8dcb6e4833de9aa5ef.css","styles-8c069d83d27a3ec9d5f0.js","1-bf7a1e468358a1ccca34.js","2-ad6b174e5148675a3605.js","component---src-pages-joyplot-tsx-7673184d17e6c4ae4411.js"],"component---src-pages-line-tsx":["styles.af8dcb6e4833de9aa5ef.css","styles-8c069d83d27a3ec9d5f0.js","1-bf7a1e468358a1ccca34.js","2-ad6b174e5148675a3605.js","3-30b331947758fee98f96.js","component---src-pages-line-tsx-f57f7ee6821b57ba78e3.js"],"component---src-pages-map-tsx":["styles.af8dcb6e4833de9aa5ef.css","styles-8c069d83d27a3ec9d5f0.js","1-bf7a1e468358a1ccca34.js","2-ad6b174e5148675a3605.js","3-30b331947758fee98f96.js","component---src-pages-map-tsx-214cc2bb04982af33158.js"],"component---src-pages-pie-tsx":["styles.af8dcb6e4833de9aa5ef.css","styles-8c069d83d27a3ec9d5f0.js","1-bf7a1e468358a1ccca34.js","2-ad6b174e5148675a3605.js","3-30b331947758fee98f96.js","component---src-pages-pie-tsx-64f81f2b2a6e9b78a221.js"],"pages-manifest":["pages-manifest-7a0fcc4ddfefa33d9874.js"]}}